code_review/__init__.py
code_review/__main__.py
code_review/cli.py
code_review/notifications.py
code_review-0.0.6.dist-info/AUTHORS.rst
code_review-0.0.6.dist-info/LICENSE
code_review-0.0.6.dist-info/METADATA
code_review-0.0.6.dist-info/WHEEL
code_review-0.0.6.dist-info/entry_points.txt
code_review-0.0.6.dist-info/top_level.txt
code_review-0.0.6.dist-info/RECORD
