Metadata-Version: 2.1
Name: code-review
Version: 0.0.6
Summary: code_review
Home-page: https://github.com/sagersmith8/code_review
Author: Sage Smith
Author-email: sagersmith8@gmail.com
License: Apache Software License 2.0
Project-URL: Changelog, https://github.com/sagersmith8/code_review/blob/master/CHANGELOG.rst
Project-URL: Issue Tracker, https://github.com/sagersmith8/code_review/issues
Platform: UNKNOWN
Classifier: Development Status :: 5 - Production/Stable
Classifier: Intended Audience :: Developers
Classifier: License :: OSI Approved :: Apache Software License
Classifier: Operating System :: Unix
Classifier: Operating System :: POSIX
Classifier: Operating System :: Microsoft :: Windows
Classifier: Programming Language :: Python
Classifier: Programming Language :: Python :: Implementation :: PyPy
Classifier: Topic :: Utilities
Requires-Python: >=3.6
Requires-Dist: pygithub
